simple_migrations/__init__.py
simple_migrations/cli.py
simple_migrations/config.py
simple_migrations/initial_setup.py
simple_migrations/migrate.py
simple_migrations/migration_template.py
simple_migrations-0.3.0.dist-info/LICENSE
simple_migrations-0.3.0.dist-info/METADATA
simple_migrations-0.3.0.dist-info/WHEEL
simple_migrations-0.3.0.dist-info/entry_points.txt
simple_migrations-0.3.0.dist-info/RECORD
