Metadata-Version: 2.1
Name: simple-migrations
Version: 0.3.0
Summary: 
Home-page: https://github.com/bp72/simple-migrations
Author: Pavel Bitiukov
Author-email: pavleg.bityukov@gmail.com
Requires-Python: >=3.11,<4.0
Classifier: Programming Language :: Python :: 3
Classifier: Programming Language :: Python :: 3.11
Classifier: Programming Language :: Python :: 3.12
Requires-Dist: configparser (>=6.0,<7.0)
Requires-Dist: psycopg (>=3.1,<4.0)
Project-URL: Repository, https://github.com/bp72/simple-migrations
